{"id":79226,"name":"精霊使いの剣舞","name_cn":"精灵使的剑舞","type":"动画","image":"c0/3b/79226_8EZ7i.jpg","link":"https://bgm.tv/subject/79226","eps":12,"collection":{"on_hold":242,"dropped":369,"wish":695,"collect":5435,"doing":219},"date":"2014-07-14","summary":"仅限冰清玉洁少女的特权——精灵契约。艾雷西亚精灵学院，贵族大小姐们汇聚于此，进行着作为精灵使应受的训练，以及精英教育。少年风早神人是世界上第二位能与精灵沟通的男性，被格雷瓦丝叫到精灵学校，在前往的路上不幸遇见了正在洗澡的学院生克蕾儿，结果被要求代替精灵与之缔结契约。就这样，风早神人成为了这个世界本不可能存在的、男性精灵使 。","rating":{"rank":7664,"total":3342,"count":{"1":14,"2":24,"3":81,"4":286,"5":845,"6":1341,"7":534,"8":149,"9":22,"10":46},"score":5.8},"updated_at":"2024-10-14T16:37:21+08:00"}